bits/__init__.py
bits/settings/__init__.py
bits_settings-1.0.5.dist-info/METADATA
bits_settings-1.0.5.dist-info/WHEEL
bits_settings-1.0.5.dist-info/top_level.txt
bits_settings-1.0.5.dist-info/RECORD
